hcl2_eval/__init__.py
hcl2_eval/api.py
hcl2_eval/error.py
hcl2_eval/py.typed
hcl2_eval/stanza.py
hcl2_eval/types.py
hcl2_eval-0.1.3.dist-info/LICENSE
hcl2_eval-0.1.3.dist-info/WHEEL
hcl2_eval-0.1.3.dist-info/METADATA
hcl2_eval-0.1.3.dist-info/RECORD
