Metadata-Version: 2.1
Name: hcl2-eval
Version: 0.1.3
Summary: 
License: MIT
Author: Niklas Rosenstein
Author-email: rosensteinniklas@gmail.com
Requires-Python: >=3.6,<4.0
Classifier: License :: OSI Approved :: MIT License
Classifier: Programming Language :: Python :: 3
Classifier: Programming Language :: Python :: 3.6
Classifier: Programming Language :: Python :: 3.7
Classifier: Programming Language :: Python :: 3.8
Classifier: Programming Language :: Python :: 3.9
Classifier: Programming Language :: Python :: 3.10
Requires-Dist: beartype (>=0.10.4,<0.11.0)
Requires-Dist: hcl2-ast (>=0.3.0,<0.4.0)
Requires-Dist: typing-extensions (>=3.10.0)
Project-URL: Bug Tracker, https://github.com/NiklasRosenstein/python-hcl2-eval/issues
Project-URL: Repository, https://github.com/NiklasRosenstein/python-hcl2-eval
